content_renderer/__init__.py
content_renderer/renderer.py
peretz_renderer-0.1.1.dist-info/METADATA
peretz_renderer-0.1.1.dist-info/WHEEL
peretz_renderer-0.1.1.dist-info/top_level.txt
peretz_renderer-0.1.1.dist-info/RECORD
