Metadata-Version: 2.1
Name: peretz-renderer
Version: 0.1.1
Summary: P3 - content renderer.
Home-page: https://github.com/me/myproject
Author: Peretz Rickett
Author-email: peretz@rickett.us
License: MIT
Platform: UNKNOWN
Classifier: License :: OSI Approved :: MIT License
Classifier: Programming Language :: Python
Classifier: Programming Language :: Python :: 3
Classifier: Programming Language :: Python :: 3.8
Classifier: Programming Language :: Python :: Implementation :: CPython
Classifier: Programming Language :: Python :: Implementation :: PyPy
Requires-Python: >=3.8.0
Requires-Dist: peretz-counter
